<?xml version="1.0" encoding="UTF-8"?>
<!DOCTYPE plist PUBLIC "-//Apple//DTD PLIST 1.0//EN" "http://www.apple.com/DTDs/PropertyList-1.0.dtd">
<plist version="1.0">
<dict>
	<key>WFQuickActionSurfaces</key>
	<array/>
	<key>WFWorkflowActions</key>
	<array>
		<dict>
			<key>WFWorkflowActionIdentifier</key>
			<string>is.workflow.actions.getmyworkflows</string>
			<key>WFWorkflowActionParameters</key>
			<dict>
				<key>UUID</key>
				<string>85A12C38-E2F4-4C86-B7B5-D1CA9BF4CA89</string>
			</dict>
		</dict>
		<dict>
			<key>WFWorkflowActionIdentifier</key>
			<string>is.workflow.actions.count</string>
			<key>WFWorkflowActionParameters</key>
			<dict>
				<key>Input</key>
				<dict>
					<key>Value</key>
					<dict>
						<key>OutputName</key>
						<string>My Shortcuts</string>
						<key>OutputUUID</key>
						<string>85A12C38-E2F4-4C86-B7B5-D1CA9BF4CA89</string>
						<key>Type</key>
						<string>ActionOutput</string>
					</dict>
					<key>WFSerializationType</key>
					<string>WFTextTokenAttachment</string>
				</dict>
				<key>UUID</key>
				<string>FB90ACD4-C92F-4274-94BD-3F8A13FE9AA9</string>
			</dict>
		</dict>
		<dict>
			<key>WFWorkflowActionIdentifier</key>
			<string>is.workflow.actions.openapp</string>
			<key>WFWorkflowActionParameters</key>
			<dict>
				<key>UUID</key>
				<string>08505CF0-6B38-42A6-ADB3-DF7C7A7656A9</string>
				<key>WFAppIdentifier</key>
				<string>AsheKube.app.a-Shell</string>
				<key>WFSelectedApp</key>
				<dict>
					<key>BundleIdentifier</key>
					<string>AsheKube.app.a-Shell</string>
					<key>Name</key>
					<string>a-Shell</string>
					<key>TeamIdentifier</key>
					<string>VG8Z23C8YL</string>
				</dict>
			</dict>
		</dict>
		<dict>
			<key>WFWorkflowActionIdentifier</key>
			<string>AsheKube.app.a-Shell.ExecuteCommandIntent</string>
			<key>WFWorkflowActionParameters</key>
			<dict>
				<key>UUID</key>
				<string>A9D3341F-DCA8-443B-A9BE-A74AB7768041</string>
				<key>command</key>
				<array>
					<string>jump Root</string>
					<string>cd iOS-Shortcuts-Gallery</string>
					<string>lg2 add .</string>
					<dict>
						<key>Value</key>
						<dict>
							<key>attachmentsByRange</key>
							<dict>
								<key>{59, 1}</key>
								<dict>
									<key>OutputName</key>
									<string>Count</string>
									<key>OutputUUID</key>
									<string>FB90ACD4-C92F-4274-94BD-3F8A13FE9AA9</string>
									<key>Type</key>
									<string>ActionOutput</string>
								</dict>
							</dict>
							<key>string</key>
							<string>lg2 commit -m "Weekly iOS Shortcuts update (numShortcuts = ￼)"</string>
						</dict>
						<key>WFSerializationType</key>
						<string>WFTextTokenString</string>
					</dict>
					<string>lg2 push</string>
				</array>
			</dict>
		</dict>
	</array>
	<key>WFWorkflowClientVersion</key>
	<string>2206.0.6</string>
	<key>WFWorkflowHasOutputFallback</key>
	<false/>
	<key>WFWorkflowHasShortcutInputVariables</key>
	<false/>
	<key>WFWorkflowIcon</key>
	<dict>
		<key>WFWorkflowIconGlyphNumber</key>
		<integer>61440</integer>
		<key>WFWorkflowIconStartColor</key>
		<integer>2846468607</integer>
	</dict>
	<key>WFWorkflowImportQuestions</key>
	<array/>
	<key>WFWorkflowInputContentItemClasses</key>
	<array>
		<string>WFAppStoreAppContentItem</string>
		<string>WFArticleContentItem</string>
		<string>WFContactContentItem</string>
		<string>WFDateContentItem</string>
		<string>WFEmailAddressContentItem</string>
		<string>WFGenericFileContentItem</string>
		<string>WFImageContentItem</string>
		<string>WFiTunesProductContentItem</string>
		<string>WFLocationContentItem</string>
		<string>WFDCMapsLinkContentItem</string>
		<string>WFAVAssetContentItem</string>
		<string>WFPDFContentItem</string>
		<string>WFPhoneNumberContentItem</string>
		<string>WFRichTextContentItem</string>
		<string>WFSafariWebPageContentItem</string>
		<string>WFStringContentItem</string>
		<string>WFURLContentItem</string>
	</array>
	<key>WFWorkflowMinimumClientVersion</key>
	<integer>900</integer>
	<key>WFWorkflowMinimumClientVersionString</key>
	<string>900</string>
	<key>WFWorkflowOutputContentItemClasses</key>
	<array/>
	<key>WFWorkflowTypes</key>
	<array>
		<string>Watch</string>
		<string>NCWidget</string>
	</array>
</dict>
</plist>
