<?xml version="1.0" encoding="UTF-8"?>
<!DOCTYPE plist PUBLIC "-//Apple//DTD PLIST 1.0//EN" "http://www.apple.com/DTDs/PropertyList-1.0.dtd">
<plist version="1.0">
<dict>
	<key>WFQuickActionSurfaces</key>
	<array/>
	<key>WFWorkflowActions</key>
	<array>
		<dict>
			<key>WFWorkflowActionIdentifier</key>
			<string>is.workflow.actions.gettext</string>
			<key>WFWorkflowActionParameters</key>
			<dict>
				<key>UUID</key>
				<string>7126C1CD-B873-4E5D-B1B1-C666A94686D8</string>
				<key>WFTextActionText</key>
				<string>Now, think very hard about these questions:</string>
			</dict>
		</dict>
		<dict>
			<key>WFWorkflowActionIdentifier</key>
			<string>is.workflow.actions.runworkflow</string>
			<key>WFWorkflowActionParameters</key>
			<dict>
				<key>UUID</key>
				<string>A56B9CB3-DCD0-4E87-A344-EE576A6B5431</string>
				<key>WFInput</key>
				<dict>
					<key>Value</key>
					<dict>
						<key>OutputName</key>
						<string>Text</string>
						<key>OutputUUID</key>
						<string>7126C1CD-B873-4E5D-B1B1-C666A94686D8</string>
						<key>Type</key>
						<string>ActionOutput</string>
					</dict>
					<key>WFSerializationType</key>
					<string>WFTextTokenAttachment</string>
				</dict>
				<key>WFWorkflow</key>
				<dict>
					<key>isSelf</key>
					<false/>
					<key>workflowIdentifier</key>
					<string>4038A604-81ED-499D-A74C-91D847B002CC</string>
					<key>workflowName</key>
					<string>Text-to-Speech (English)</string>
				</dict>
				<key>WFWorkflowName</key>
				<string>Text-to-Speech (English)</string>
			</dict>
		</dict>
		<dict>
			<key>WFWorkflowActionIdentifier</key>
			<string>is.workflow.actions.delay</string>
			<key>WFWorkflowActionParameters</key>
			<dict>
				<key>WFDelayTime</key>
				<real>2</real>
			</dict>
		</dict>
		<dict>
			<key>WFWorkflowActionIdentifier</key>
			<string>is.workflow.actions.gettext</string>
			<key>WFWorkflowActionParameters</key>
			<dict>
				<key>UUID</key>
				<string>AE265353-CDEE-457B-AE52-9E9F032B0E48</string>
				<key>WFTextActionText</key>
				<string>What would Tomorrow Me want Today Me to do in the present moment?</string>
			</dict>
		</dict>
		<dict>
			<key>WFWorkflowActionIdentifier</key>
			<string>is.workflow.actions.runworkflow</string>
			<key>WFWorkflowActionParameters</key>
			<dict>
				<key>UUID</key>
				<string>3D4FBA7E-FA51-4280-B59B-87DC42AE1EFA</string>
				<key>WFInput</key>
				<dict>
					<key>Value</key>
					<dict>
						<key>OutputName</key>
						<string>Text</string>
						<key>OutputUUID</key>
						<string>AE265353-CDEE-457B-AE52-9E9F032B0E48</string>
						<key>Type</key>
						<string>ActionOutput</string>
					</dict>
					<key>WFSerializationType</key>
					<string>WFTextTokenAttachment</string>
				</dict>
				<key>WFWorkflow</key>
				<dict>
					<key>isSelf</key>
					<false/>
					<key>workflowIdentifier</key>
					<string>4038A604-81ED-499D-A74C-91D847B002CC</string>
					<key>workflowName</key>
					<string>Text-to-Speech (English)</string>
				</dict>
				<key>WFWorkflowName</key>
				<string>Text-to-Speech (English)</string>
			</dict>
		</dict>
		<dict>
			<key>WFWorkflowActionIdentifier</key>
			<string>is.workflow.actions.delay</string>
			<key>WFWorkflowActionParameters</key>
			<dict>
				<key>WFDelayTime</key>
				<real>2</real>
			</dict>
		</dict>
		<dict>
			<key>WFWorkflowActionIdentifier</key>
			<string>is.workflow.actions.gettext</string>
			<key>WFWorkflowActionParameters</key>
			<dict>
				<key>UUID</key>
				<string>6B5CB429-A59F-4E29-9C9B-5194CCAC6509</string>
				<key>WFTextActionText</key>
				<string>Which decisions and actions would the Ideal Me make and take?</string>
			</dict>
		</dict>
		<dict>
			<key>WFWorkflowActionIdentifier</key>
			<string>is.workflow.actions.runworkflow</string>
			<key>WFWorkflowActionParameters</key>
			<dict>
				<key>UUID</key>
				<string>136D8336-E088-441B-8605-8E397A07330A</string>
				<key>WFInput</key>
				<dict>
					<key>Value</key>
					<dict>
						<key>OutputName</key>
						<string>Text</string>
						<key>OutputUUID</key>
						<string>6B5CB429-A59F-4E29-9C9B-5194CCAC6509</string>
						<key>Type</key>
						<string>ActionOutput</string>
					</dict>
					<key>WFSerializationType</key>
					<string>WFTextTokenAttachment</string>
				</dict>
				<key>WFWorkflow</key>
				<dict>
					<key>isSelf</key>
					<false/>
					<key>workflowIdentifier</key>
					<string>4038A604-81ED-499D-A74C-91D847B002CC</string>
					<key>workflowName</key>
					<string>Text-to-Speech (English)</string>
				</dict>
				<key>WFWorkflowName</key>
				<string>Text-to-Speech (English)</string>
			</dict>
		</dict>
		<dict>
			<key>WFWorkflowActionIdentifier</key>
			<string>is.workflow.actions.delay</string>
			<key>WFWorkflowActionParameters</key>
			<dict>
				<key>WFDelayTime</key>
				<real>2</real>
			</dict>
		</dict>
		<dict>
			<key>WFWorkflowActionIdentifier</key>
			<string>is.workflow.actions.gettext</string>
			<key>WFWorkflowActionParameters</key>
			<dict>
				<key>UUID</key>
				<string>C2EDEC10-E05A-455D-A464-A64892E6E221</string>
				<key>WFTextActionText</key>
				<string>Am I getting better every single day? Did I beat Yesterday Me?</string>
			</dict>
		</dict>
		<dict>
			<key>WFWorkflowActionIdentifier</key>
			<string>is.workflow.actions.runworkflow</string>
			<key>WFWorkflowActionParameters</key>
			<dict>
				<key>UUID</key>
				<string>56CF6CFD-E5F0-432E-8591-0A1EBDA3820D</string>
				<key>WFInput</key>
				<dict>
					<key>Value</key>
					<dict>
						<key>OutputName</key>
						<string>Text</string>
						<key>OutputUUID</key>
						<string>C2EDEC10-E05A-455D-A464-A64892E6E221</string>
						<key>Type</key>
						<string>ActionOutput</string>
					</dict>
					<key>WFSerializationType</key>
					<string>WFTextTokenAttachment</string>
				</dict>
				<key>WFWorkflow</key>
				<dict>
					<key>isSelf</key>
					<false/>
					<key>workflowIdentifier</key>
					<string>4038A604-81ED-499D-A74C-91D847B002CC</string>
					<key>workflowName</key>
					<string>Text-to-Speech (English)</string>
				</dict>
				<key>WFWorkflowName</key>
				<string>Text-to-Speech (English)</string>
			</dict>
		</dict>
		<dict>
			<key>WFWorkflowActionIdentifier</key>
			<string>is.workflow.actions.delay</string>
			<key>WFWorkflowActionParameters</key>
			<dict>
				<key>WFDelayTime</key>
				<real>2</real>
			</dict>
		</dict>
		<dict>
			<key>WFWorkflowActionIdentifier</key>
			<string>is.workflow.actions.gettext</string>
			<key>WFWorkflowActionParameters</key>
			<dict>
				<key>UUID</key>
				<string>11A87D62-C71D-490B-AB34-3B45A43D0328</string>
				<key>WFTextActionText</key>
				<string>What would my greatest day look like TODAY?
</string>
			</dict>
		</dict>
		<dict>
			<key>WFWorkflowActionIdentifier</key>
			<string>is.workflow.actions.runworkflow</string>
			<key>WFWorkflowActionParameters</key>
			<dict>
				<key>UUID</key>
				<string>516C755C-DDAE-4F31-9453-1C0706010F1B</string>
				<key>WFInput</key>
				<dict>
					<key>Value</key>
					<dict>
						<key>OutputName</key>
						<string>Text</string>
						<key>OutputUUID</key>
						<string>11A87D62-C71D-490B-AB34-3B45A43D0328</string>
						<key>Type</key>
						<string>ActionOutput</string>
					</dict>
					<key>WFSerializationType</key>
					<string>WFTextTokenAttachment</string>
				</dict>
				<key>WFWorkflow</key>
				<dict>
					<key>isSelf</key>
					<false/>
					<key>workflowIdentifier</key>
					<string>4038A604-81ED-499D-A74C-91D847B002CC</string>
					<key>workflowName</key>
					<string>Text-to-Speech (English)</string>
				</dict>
				<key>WFWorkflowName</key>
				<string>Text-to-Speech (English)</string>
			</dict>
		</dict>
		<dict>
			<key>WFWorkflowActionIdentifier</key>
			<string>is.workflow.actions.delay</string>
			<key>WFWorkflowActionParameters</key>
			<dict>
				<key>WFDelayTime</key>
				<real>2</real>
			</dict>
		</dict>
		<dict>
			<key>WFWorkflowActionIdentifier</key>
			<string>is.workflow.actions.gettext</string>
			<key>WFWorkflowActionParameters</key>
			<dict>
				<key>UUID</key>
				<string>56C095A0-56A0-48C9-9FB4-09D1DB578A8A</string>
				<key>WFTextActionText</key>
				<string>What is today's adventure going to be?</string>
			</dict>
		</dict>
		<dict>
			<key>WFWorkflowActionIdentifier</key>
			<string>is.workflow.actions.runworkflow</string>
			<key>WFWorkflowActionParameters</key>
			<dict>
				<key>UUID</key>
				<string>69959F1F-1C11-4AD6-9E91-4F5C8BF95A33</string>
				<key>WFInput</key>
				<dict>
					<key>Value</key>
					<dict>
						<key>OutputName</key>
						<string>Text</string>
						<key>OutputUUID</key>
						<string>56C095A0-56A0-48C9-9FB4-09D1DB578A8A</string>
						<key>Type</key>
						<string>ActionOutput</string>
					</dict>
					<key>WFSerializationType</key>
					<string>WFTextTokenAttachment</string>
				</dict>
				<key>WFWorkflow</key>
				<dict>
					<key>isSelf</key>
					<false/>
					<key>workflowIdentifier</key>
					<string>4038A604-81ED-499D-A74C-91D847B002CC</string>
					<key>workflowName</key>
					<string>Text-to-Speech (English)</string>
				</dict>
				<key>WFWorkflowName</key>
				<string>Text-to-Speech (English)</string>
			</dict>
		</dict>
	</array>
	<key>WFWorkflowClientVersion</key>
	<string>2302.0.5</string>
	<key>WFWorkflowHasOutputFallback</key>
	<false/>
	<key>WFWorkflowHasShortcutInputVariables</key>
	<false/>
	<key>WFWorkflowIcon</key>
	<dict>
		<key>WFWorkflowIconGlyphNumber</key>
		<integer>61440</integer>
		<key>WFWorkflowIconStartColor</key>
		<integer>2846468607</integer>
	</dict>
	<key>WFWorkflowImportQuestions</key>
	<array>
		<dict>
			<key>ActionIndex</key>
			<integer>0</integer>
			<key>Category</key>
			<string>Parameter</string>
			<key>DefaultValue</key>
			<string></string>
			<key>ParameterKey</key>
			<string>WFTextActionText</string>
			<key>Text</key>
			<string>What is your first name?</string>
		</dict>
	</array>
	<key>WFWorkflowInputContentItemClasses</key>
	<array>
		<string>WFAppStoreAppContentItem</string>
		<string>WFArticleContentItem</string>
		<string>WFContactContentItem</string>
		<string>WFDateContentItem</string>
		<string>WFEmailAddressContentItem</string>
		<string>WFGenericFileContentItem</string>
		<string>WFImageContentItem</string>
		<string>WFiTunesProductContentItem</string>
		<string>WFLocationContentItem</string>
		<string>WFDCMapsLinkContentItem</string>
		<string>WFAVAssetContentItem</string>
		<string>WFPDFContentItem</string>
		<string>WFPhoneNumberContentItem</string>
		<string>WFRichTextContentItem</string>
		<string>WFSafariWebPageContentItem</string>
		<string>WFStringContentItem</string>
		<string>WFURLContentItem</string>
	</array>
	<key>WFWorkflowMinimumClientVersion</key>
	<integer>900</integer>
	<key>WFWorkflowMinimumClientVersionString</key>
	<string>900</string>
	<key>WFWorkflowOutputContentItemClasses</key>
	<array/>
	<key>WFWorkflowTypes</key>
	<array>
		<string>NCWidget</string>
	</array>
</dict>
</plist>
